connector_vk_private_lib/__init__.py
connector_vk_private_lib/src/__init__.py
connector_vk_private_lib/src/main.py
connector_vk_private_lib/src/config/__init__.py
connector_vk_private_lib/src/config/main.py
connector_vk_private_lib/src/interfaces/__init__.py
connector_vk_private_lib/src/interfaces/account.py
connector_vk_private_lib/src/interfaces/ads.py
connector_vk_private_lib/src/interfaces/attachments.py
connector_vk_private_lib/src/interfaces/audio.py
connector_vk_private_lib/src/interfaces/audioads.py
connector_vk_private_lib/src/interfaces/groups.py
connector_vk_private_lib/src/interfaces/main.py
connector_vk_private_lib/src/interfaces/photo.py
connector_vk_private_lib/src/interfaces/video.py
connector_vk_private_lib/src/interfaces/wall.py
connector_vk_private_lib/src/service/__init__.py
connector_vk_private_lib/src/service/main.py
connector_vk_private_lib-0.2.5.dist-info/LICENSE
connector_vk_private_lib-0.2.5.dist-info/METADATA
connector_vk_private_lib-0.2.5.dist-info/WHEEL
connector_vk_private_lib-0.2.5.dist-info/top_level.txt
connector_vk_private_lib-0.2.5.dist-info/RECORD
